wg_qrotator/__init__.py
wg_qrotator/cli.py
wg_qrotator/config_parser.py
wg_qrotator/constants.py
wg_qrotator/exceptions.py
wg_qrotator/handshake.py
wg_qrotator/key_gen.py
wg_qrotator/kms.py
wg_qrotator/peer.py
wg_qrotator/qrotator.py
wg_qrotator/rotate.py
wg_qrotator/storage.py
wg_qrotator/wg_key_rotation_scheduler.py
wg_qrotator/kms_so/README.md
wg_qrotator/kms_so/libclient_api.so
wg_qrotator/kms_so/libclient_api_structs.py
wg_qrotator-0.1.4.dist-info/METADATA
wg_qrotator-0.1.4.dist-info/WHEEL
wg_qrotator-0.1.4.dist-info/entry_points.txt
wg_qrotator-0.1.4.dist-info/licenses/LICENSE
wg_qrotator-0.1.4.dist-info/RECORD
