Metadata-Version: 2.4
Name: wg-Qrotator
Version: 0.1.4
Summary: The quantum-enabled hybrid key rotator for WireGuard tunnels.
Project-URL: Documentation, https://quantum-communication-group.github.io/wg-Qrotator
Project-URL: Repository, https://github.com/Quantum-Communication-Group/wg-Qrotator
Project-URL: Bug Tracker, https://github.com/Quantum-Communication-Group/wg-Qrotator/issues
Author-email: Diogo Filipe Matos <dftm@ua.pt>, Armando Nolasco Pinto <anp@ua.pt>
Maintainer-email: Diogo Filipe Matos <dftm@ua.pt>
License-File: LICENSE
Keywords: PQC,QKD,VPN,key rotator,post-quantum,quantum,tunneling
Requires-Python: >=3.10
Requires-Dist: filelock==3.19.1
Requires-Dist: keyring==25.6.0
Requires-Dist: keyrings-alt==5.0.2
Requires-Dist: netifaces==0.11.0
Requires-Dist: psutil==7.1.0
Requires-Dist: pycryptodome==3.23.0
Requires-Dist: pyyaml==6.0.2
Requires-Dist: requests==2.32.5
Requires-Dist: schema==0.7.7
Requires-Dist: wolfcrypt==5.8.2.post0
